{
  "generated_at": "2026-03-21T09:39:02+00:00",
  "properties": [
    {
      "name": "59 Oak Lane",
      "events": [
        {
          "uid": "2b02eecf-5cc6-49fe-ab12-ca601ff07de5",
          "summary": "Owner Block",
          "type": "closed",
          "start": "2026-01-01",
          "end": "2026-09-11"
        }
      ]
    },
    {
      "name": "111 Eagles",
      "events": [
        {
          "uid": "fa672350-c8b5-4e42-9c75-f2137eb9ced4",
          "summary": "Reservation",
          "type": "reservation",
          "start": "2026-01-01",
          "end": "2026-01-03"
        },
        {
          "uid": "6e134820-5c25-4b4b-adb8-a00b7c7eb96c",
          "summary": "Reservation",
          "type": "reservation",
          "start": "2026-01-03",
          "end": "2026-01-06"
        },
        {
          "uid": "3a8f402d-4401-44d2-b8c2-c1c19c055edd",
          "summary": "Reservation",
          "type": "reservation",
          "start": "2026-01-09",
          "end": "2026-01-11"
        },
        {
          "uid": "c3d01618-9f42-4028-8896-46f59bf4faab",
          "summary": "Reservation",
          "type": "reservation",
          "start": "2026-01-16",
          "end": "2026-01-19"
        },
        {
          "uid": "1957679d-35cc-4f3f-be97-be88e869e782",
          "summary": "Owner Block",
          "type": "closed",
          "start": "2026-01-21",
          "end": "2026-01-22"
        },
        {
          "uid": "b8bc3d2b-5871-4f5c-a76c-dd5fc4b18a7e",
          "summary": "Reservation",
          "type": "reservation",
          "start": "2026-01-22",
          "end": "2026-01-25"
        },
        {
          "uid": "f4111b18-6f1c-4592-9901-2c251e1343f3",
          "summary": "Reservation",
          "type": "reservation",
          "start": "2026-01-25",
          "end": "2026-01-28"
        },
        {
          "uid": "d60508a7-8229-4459-a9c2-41438f5b3529",
          "summary": "Owner Block",
          "type": "closed",
          "start": "2026-01-29",
          "end": "2026-01-30"
        },
        {
          "uid": "fea0556e-5528-4e98-a58f-5110b389c2af",
          "summary": "Reservation",
          "type": "reservation",
          "start": "2026-01-30",
          "end": "2026-02-01"
        },
        {
          "uid": "4a2f6bb1-3e82-4b5c-a2d1-b8a9a90c0c6d",
          "summary": "Reservation",
          "type": "reservation",
          "start": "2026-02-05",
          "end": "2026-02-08"
        },
        {
          "uid": "390d60b5-506c-4606-bb67-2c744ec5493d",
          "summary": "Reservation",
          "type": "reservation",
          "start": "2026-02-08",
          "end": "2026-02-12"
        },
        {
          "uid": "395d5cc8-38fc-481c-bb05-f3048d84e74d",
          "summary": "Reservation",
          "type": "reservation",
          "start": "2026-02-13",
          "end": "2026-02-16"
        },
        {
          "uid": "b9eb8b5c-857b-407d-a7ff-db7169639ee3",
          "summary": "Reservation",
          "type": "reservation",
          "start": "2026-02-19",
          "end": "2026-02-22"
        },
        {
          "uid": "d5d3b168-6f72-477c-8b7f-654e90197443",
          "summary": "Reservation",
          "type": "reservation",
          "start": "2026-02-22",
          "end": "2026-02-24"
        },
        {
          "uid": "de1dd7a1-6684-48ca-bdd0-bdc2d93e7150",
          "summary": "Reservation",
          "type": "reservation",
          "start": "2026-02-25",
          "end": "2026-02-28"
        },
        {
          "uid": "3b818bed-f0f5-4cc5-bfc3-6f93f44a1fd6",
          "summary": "Reservation",
          "type": "reservation",
          "start": "2026-02-28",
          "end": "2026-03-03"
        },
        {
          "uid": "aff23140-6acf-4f1a-b7d7-647872fece08",
          "summary": "Reservation",
          "type": "reservation",
          "start": "2026-03-06",
          "end": "2026-03-08"
        },
        {
          "uid": "cc62d87d-b28c-423d-992a-a68212cada2c",
          "summary": "Reservation",
          "type": "reservation",
          "start": "2026-03-13",
          "end": "2026-03-15"
        }
      ]
    },
    {
      "name": "119 Pedlars Point",
      "events": [
        {
          "uid": "697ecf0c-a0ed-4b58-a895-a177948e59cf",
          "summary": "Reservation",
          "type": "reservation",
          "start": "2026-01-01",
          "end": "2026-01-04"
        },
        {
          "uid": "4973e862-cb5b-44e6-ba87-1900676734da",
          "summary": "Reservation",
          "type": "reservation",
          "start": "2026-01-16",
          "end": "2026-01-19"
        },
        {
          "uid": "a89e4b25-206b-4e28-b931-9b5a83da500b",
          "summary": "Owner Block",
          "type": "closed",
          "start": "2026-01-21",
          "end": "2026-01-24"
        },
        {
          "uid": "8606609d-4b16-42e6-90bb-2ecc4cbadb4d",
          "summary": "Reservation",
          "type": "reservation",
          "start": "2026-01-24",
          "end": "2026-01-27"
        },
        {
          "uid": "3fbeda7e-1685-4e6e-b945-d1c06945404b",
          "summary": "Owner Block",
          "type": "closed",
          "start": "2026-01-27",
          "end": "2026-01-29"
        },
        {
          "uid": "8fbd5245-be21-4c00-8274-810703cfca08",
          "summary": "Reservation",
          "type": "reservation",
          "start": "2026-01-29",
          "end": "2026-02-02"
        },
        {
          "uid": "13d13f9f-561b-46b1-a854-33d6776fe0f5",
          "summary": "Reservation",
          "type": "reservation",
          "start": "2026-02-06",
          "end": "2026-02-08"
        },
        {
          "uid": "d36fb137-c9ca-4d30-be00-e0505c7bb13c",
          "summary": "Reservation",
          "type": "reservation",
          "start": "2026-02-14",
          "end": "2026-02-16"
        },
        {
          "uid": "2262e338-5e8c-45f0-b9b8-27356b655174",
          "summary": "Reservation",
          "type": "reservation",
          "start": "2026-02-19",
          "end": "2026-02-22"
        },
        {
          "uid": "621aa04b-f30a-42c6-b33c-621a55acb64d",
          "summary": "Owner Block",
          "type": "closed",
          "start": "2026-02-22",
          "end": "2026-02-23"
        },
        {
          "uid": "c8d96229-57b5-4615-9aea-c451390f0ed6",
          "summary": "Reservation",
          "type": "reservation",
          "start": "2026-02-27",
          "end": "2026-03-01"
        },
        {
          "uid": "d07755d9-1ac3-43c4-9658-cb6a1d9aedc5",
          "summary": "Owner Block",
          "type": "closed",
          "start": "2026-03-13",
          "end": "2026-03-31"
        },
        {
          "uid": "922b5ca0-4577-4955-9bfa-782c87ff31f8",
          "summary": "Reservation",
          "type": "reservation",
          "start": "2026-04-22",
          "end": "2026-04-25"
        },
        {
          "uid": "ae5a0c8d-8e12-42d5-83e5-1f50649bdb02",
          "summary": "Reservation",
          "type": "reservation",
          "start": "2026-05-15",
          "end": "2026-05-17"
        },
        {
          "uid": "fa74560c-0886-4eab-ad9f-71b2554c76bb",
          "summary": "Reservation",
          "type": "reservation",
          "start": "2026-09-11",
          "end": "2026-09-13"
        }
      ]
    },
    {
      "name": "1923 High Ridge",
      "events": [
        {
          "uid": "cb26baa5-6133-4a36-a917-3d28daca5910",
          "summary": "Owner Block",
          "type": "closed",
          "start": "2026-01-01",
          "end": "2026-01-04"
        },
        {
          "uid": "b2bb2c58-8b62-4da8-a0db-8b304d4d987d",
          "summary": "Owner Block",
          "type": "closed",
          "start": "2026-01-11",
          "end": "2026-01-13"
        },
        {
          "uid": "60e94ef2-a040-4777-b924-dea1795c84e0",
          "summary": "Reservation",
          "type": "reservation",
          "start": "2026-01-16",
          "end": "2026-01-19"
        },
        {
          "uid": "27763b3b-cee6-40ab-aff3-4b3a9fac2ebd",
          "summary": "Owner Block",
          "type": "closed",
          "start": "2026-01-21",
          "end": "2026-01-23"
        },
        {
          "uid": "b57747ed-bd9b-42ac-9631-0fec1676c9a6",
          "summary": "Reservation",
          "type": "reservation",
          "start": "2026-01-23",
          "end": "2026-01-26"
        },
        {
          "uid": "9ed30df4-2cb8-49f8-8106-4408b8561242",
          "summary": "Owner Block",
          "type": "closed",
          "start": "2026-01-26",
          "end": "2026-01-30"
        },
        {
          "uid": "2a543c78-c5d2-4e00-a89e-13c1fb178b41",
          "summary": "Reservation",
          "type": "reservation",
          "start": "2026-01-30",
          "end": "2026-02-01"
        },
        {
          "uid": "0390ab15-381e-4c99-af0d-984db671564a",
          "summary": "Owner Block",
          "type": "closed",
          "start": "2026-02-01",
          "end": "2026-02-02"
        },
        {
          "uid": "0b372256-e772-4528-8829-bcf710b7602b",
          "summary": "Reservation",
          "type": "reservation",
          "start": "2026-02-06",
          "end": "2026-02-09"
        },
        {
          "uid": "3ebf6deb-a018-4373-b376-85696d77e045",
          "summary": "Reservation",
          "type": "reservation",
          "start": "2026-02-13",
          "end": "2026-02-15"
        },
        {
          "uid": "9c809ab4-937b-444e-b38d-bd9cf3d81a98",
          "summary": "Reservation",
          "type": "reservation",
          "start": "2026-02-15",
          "end": "2026-02-17"
        },
        {
          "uid": "67ce3a60-6d82-4bbc-b318-9e606cc744c0",
          "summary": "Reservation",
          "type": "reservation",
          "start": "2026-02-20",
          "end": "2026-02-23"
        },
        {
          "uid": "e9bcc138-21d7-4025-840f-8806984114e5",
          "summary": "Owner Block",
          "type": "closed",
          "start": "2026-02-24",
          "end": "2026-02-27"
        },
        {
          "uid": "c0a6a0d6-5d99-4b7b-9579-0a0b1923e2d7",
          "summary": "Reservation",
          "type": "reservation",
          "start": "2026-02-27",
          "end": "2026-03-01"
        },
        {
          "uid": "798f015e-129e-47c8-a6ca-9aa81b2fb8cd",
          "summary": "Reservation",
          "type": "reservation",
          "start": "2026-03-08",
          "end": "2026-03-10"
        },
        {
          "uid": "9facebf5-418d-45d8-b98d-058a21b04520",
          "summary": "Owner Block",
          "type": "closed",
          "start": "2026-03-11",
          "end": "2026-03-13"
        },
        {
          "uid": "a06d9ee1-9736-472e-b6ed-440bbd0f728f",
          "summary": "Reservation",
          "type": "reservation",
          "start": "2026-03-13",
          "end": "2026-03-15"
        },
        {
          "uid": "0b05c838-0dff-42b9-b7bf-4f161bfd7cb3",
          "summary": "Reservation",
          "type": "reservation",
          "start": "2026-03-20",
          "end": "2026-03-22"
        },
        {
          "uid": "f57a20cf-a1df-444e-97f6-b7ad91634bee",
          "summary": "Reservation",
          "type": "reservation",
          "start": "2026-03-26",
          "end": "2026-03-29"
        },
        {
          "uid": "023e2eb9-d15b-46bb-b435-1b11377554c8",
          "summary": "Reservation",
          "type": "reservation",
          "start": "2026-04-02",
          "end": "2026-04-04"
        },
        {
          "uid": "330030f7-1043-4375-96e4-3576fbd945a1",
          "summary": "Reservation",
          "type": "reservation",
          "start": "2026-06-03",
          "end": "2026-06-06"
        },
        {
          "uid": "1761e9fc-073d-49f2-a1e5-256cffc4123a",
          "summary": "Reservation",
          "type": "reservation",
          "start": "2026-06-19",
          "end": "2026-06-22"
        },
        {
          "uid": "b80a87ba-f91a-4ab3-9186-0026e9013228",
          "summary": "Reservation",
          "type": "reservation",
          "start": "2026-07-01",
          "end": "2026-07-31"
        }
      ]
    },
    {
      "name": "327 Crawfords Edge",
      "events": [
        {
          "uid": "c4eff966-398e-4257-942f-5b91b5b1efc6",
          "summary": "Reservation",
          "type": "reservation",
          "start": "2026-01-01",
          "end": "2026-01-04"
        },
        {
          "uid": "204bc3e1-4ac6-4d22-a5cf-7850e6ea549b",
          "summary": "Owner Block",
          "type": "closed",
          "start": "2026-01-12",
          "end": "2026-01-19"
        },
        {
          "uid": "f3c9abcf-b1b7-4b93-a53c-a0f9e6b5092f",
          "summary": "Owner Block",
          "type": "closed",
          "start": "2026-01-21",
          "end": "2026-01-24"
        },
        {
          "uid": "697eebfa-642f-474d-8681-2bb7bd509c5d",
          "summary": "Reservation",
          "type": "reservation",
          "start": "2026-01-24",
          "end": "2026-01-26"
        },
        {
          "uid": "fe319a74-c75a-473c-befe-7672a8ebbea6",
          "summary": "Owner Block",
          "type": "closed",
          "start": "2026-01-26",
          "end": "2026-01-29"
        },
        {
          "uid": "8e555161-9ce7-46ea-99bf-24adea368c93",
          "summary": "Reservation",
          "type": "reservation",
          "start": "2026-02-05",
          "end": "2026-02-08"
        },
        {
          "uid": "7de78c09-44b5-400d-9e91-58d4fc18319a",
          "summary": "Reservation",
          "type": "reservation",
          "start": "2026-02-14",
          "end": "2026-02-16"
        },
        {
          "uid": "a7656dba-cc77-40da-8bd2-e14a83ce0268",
          "summary": "Owner Block",
          "type": "closed",
          "start": "2026-02-19",
          "end": "2026-02-23"
        },
        {
          "uid": "13d85455-1af3-4406-827b-5e1475c5df12",
          "summary": "Reservation",
          "type": "reservation",
          "start": "2026-03-05",
          "end": "2026-03-08"
        },
        {
          "uid": "a40c4064-9862-4972-978e-cdf29c60b917",
          "summary": "Owner Block",
          "type": "closed",
          "start": "2026-03-19",
          "end": "2026-03-23"
        },
        {
          "uid": "adc9b1f5-1551-416a-b8eb-cbf75659adca",
          "summary": "Reservation",
          "type": "reservation",
          "start": "2026-03-26",
          "end": "2026-03-29"
        },
        {
          "uid": "379f2efe-f1f8-4ba6-9c24-dc6c012e2245",
          "summary": "Reservation",
          "type": "reservation",
          "start": "2026-04-03",
          "end": "2026-04-05"
        },
        {
          "uid": "d85a21b6-dcb2-457e-af7c-79dea85dad88",
          "summary": "Owner Block",
          "type": "closed",
          "start": "2026-04-07",
          "end": "2026-04-11"
        },
        {
          "uid": "eb1fc2ca-b5af-4f4c-8006-277c43b21333",
          "summary": "Reservation",
          "type": "reservation",
          "start": "2026-04-24",
          "end": "2026-04-26"
        },
        {
          "uid": "3c540279-3d8a-44da-bd17-2c5521c31715",
          "summary": "Reservation",
          "type": "reservation",
          "start": "2026-04-26",
          "end": "2026-05-03"
        },
        {
          "uid": "2c183089-755c-4647-a2ba-7f22e9615de6",
          "summary": "Reservation",
          "type": "reservation",
          "start": "2026-05-07",
          "end": "2026-05-10"
        },
        {
          "uid": "f3f948a3-9a5b-43ee-ac8a-d48d9cdd9586",
          "summary": "Reservation",
          "type": "reservation",
          "start": "2026-05-21",
          "end": "2026-05-26"
        },
        {
          "uid": "5da0c021-3494-4a3b-8878-b26d6342bd9f",
          "summary": "Reservation",
          "type": "reservation",
          "start": "2026-05-28",
          "end": "2026-06-01"
        },
        {
          "uid": "7f5a826c-4d62-4fb5-a90b-f092fb8c92c4",
          "summary": "Reservation",
          "type": "reservation",
          "start": "2026-06-12",
          "end": "2026-06-15"
        },
        {
          "uid": "16869d89-b0dc-4c82-9f42-d977e41dd78e",
          "summary": "Owner Block",
          "type": "closed",
          "start": "2026-06-18",
          "end": "2026-08-28"
        }
      ]
    },
    {
      "name": "333 Dobie",
      "events": [
        {
          "uid": "265190c8-76c4-4e54-86c2-0d762673dc83",
          "summary": "Reservation",
          "type": "reservation",
          "start": "2026-01-01",
          "end": "2026-01-02"
        },
        {
          "uid": "d65c0c2f-00b2-4c3b-8557-c3461a2402cc",
          "summary": "Reservation",
          "type": "reservation",
          "start": "2026-01-02",
          "end": "2026-01-04"
        },
        {
          "uid": "4b83cd86-c41f-448d-b7df-2f40d4977cdd",
          "summary": "Reservation",
          "type": "reservation",
          "start": "2026-01-05",
          "end": "2026-01-08"
        },
        {
          "uid": "b44d4052-a26f-4d53-8e2f-fcee19e57814",
          "summary": "Owner Block",
          "type": "closed",
          "start": "2026-01-08",
          "end": "2026-01-09"
        },
        {
          "uid": "8712cdec-2cd8-4922-bb3b-83fc3be31050",
          "summary": "Reservation",
          "type": "reservation",
          "start": "2026-01-09",
          "end": "2026-01-11"
        },
        {
          "uid": "e70c1991-a4ba-4bc1-bc99-332c771656ec",
          "summary": "Reservation",
          "type": "reservation",
          "start": "2026-01-16",
          "end": "2026-01-19"
        },
        {
          "uid": "0d7240a4-2c10-4f97-ae5b-106398ccafa2",
          "summary": "Owner Block",
          "type": "closed",
          "start": "2026-01-19",
          "end": "2026-01-21"
        },
        {
          "uid": "683c0b92-8b8f-46b5-9fc4-917e7c8b8e9d",
          "summary": "Reservation",
          "type": "reservation",
          "start": "2026-01-21",
          "end": "2026-01-24"
        },
        {
          "uid": "458e8c55-b8eb-4b21-838e-fa62e7289e4b",
          "summary": "Reservation",
          "type": "reservation",
          "start": "2026-01-24",
          "end": "2026-01-29"
        },
        {
          "uid": "15732ddb-f4cc-4959-8713-b26b54892bb1",
          "summary": "Owner Block",
          "type": "closed",
          "start": "2026-01-29",
          "end": "2026-01-30"
        },
        {
          "uid": "8ed4c49a-a0ba-4b8a-9db4-15ba2c041433",
          "summary": "Reservation",
          "type": "reservation",
          "start": "2026-01-30",
          "end": "2026-02-01"
        },
        {
          "uid": "a75e02cb-6aaf-4f22-9d9f-295d7497b170",
          "summary": "Reservation",
          "type": "reservation",
          "start": "2026-02-03",
          "end": "2026-02-06"
        },
        {
          "uid": "82a2feae-9bee-4014-b447-393ba6b28c88",
          "summary": "Reservation",
          "type": "reservation",
          "start": "2026-02-06",
          "end": "2026-02-08"
        },
        {
          "uid": "faa0d995-0720-4e47-916d-3a8acde07917",
          "summary": "Reservation",
          "type": "reservation",
          "start": "2026-02-09",
          "end": "2026-02-13"
        },
        {
          "uid": "7dc9fce6-a266-40bc-8616-0449eee54dad",
          "summary": "Reservation",
          "type": "reservation",
          "start": "2026-02-13",
          "end": "2026-02-16"
        },
        {
          "uid": "fed64b71-e616-4b07-b0b3-e788680833a5",
          "summary": "Reservation",
          "type": "reservation",
          "start": "2026-02-16",
          "end": "2026-02-18"
        },
        {
          "uid": "79e054f5-be22-44eb-996e-bbebf107a642",
          "summary": "Reservation",
          "type": "reservation",
          "start": "2026-02-19",
          "end": "2026-02-23"
        },
        {
          "uid": "2a933c31-340b-4c48-ae94-f925e36072ac",
          "summary": "Reservation",
          "type": "reservation",
          "start": "2026-02-26",
          "end": "2026-03-01"
        },
        {
          "uid": "8059b706-e6da-4c62-85c5-0430aca51b38",
          "summary": "Reservation",
          "type": "reservation",
          "start": "2026-03-05",
          "end": "2026-03-08"
        },
        {
          "uid": "7bbb84b3-c0a4-470a-8912-242aeb7b9c0e",
          "summary": "Reservation",
          "type": "reservation",
          "start": "2026-04-06",
          "end": "2026-04-09"
        },
        {
          "uid": "07f6da4c-b93b-43c2-b8ec-9a89f0d3c1ef",
          "summary": "Owner Block",
          "type": "closed",
          "start": "2026-04-10",
          "end": "2026-04-15"
        },
        {
          "uid": "9306defd-acf3-4282-b167-320e4d406342",
          "summary": "Reservation",
          "type": "reservation",
          "start": "2026-04-23",
          "end": "2026-04-26"
        },
        {
          "uid": "2237139b-516b-4d69-9623-9429f111378d",
          "summary": "Reservation",
          "type": "reservation",
          "start": "2026-05-14",
          "end": "2026-05-17"
        },
        {
          "uid": "cc487bc6-4ad0-4bf7-a9c9-645bdefc6b2d",
          "summary": "Reservation",
          "type": "reservation",
          "start": "2027-01-22",
          "end": "2027-01-26"
        },
        {
          "uid": "cde8df4d-132e-4985-bb82-ec2d33a5866d",
          "summary": "Reservation",
          "type": "reservation",
          "start": "2027-01-29",
          "end": "2027-01-31"
        },
        {
          "uid": "d321a82e-e4dd-404d-acb7-21f93c526956",
          "summary": "Reservation",
          "type": "reservation",
          "start": "2027-02-03",
          "end": "2027-02-05"
        },
        {
          "uid": "fe203f7b-f72e-4806-8c72-275fec65f0c1",
          "summary": "Reservation",
          "type": "reservation",
          "start": "2027-02-05",
          "end": "2027-02-07"
        },
        {
          "uid": "721fedab-0021-46f1-87d0-307f4415536b",
          "summary": "Reservation",
          "type": "reservation",
          "start": "2027-02-14",
          "end": "2027-02-16"
        }
      ]
    },
    {
      "name": "61 Bear Run",
      "events": [
        {
          "uid": "9b753de0-9a3e-4de6-ad15-c8d2f8c084ea",
          "summary": "Reservation",
          "type": "reservation",
          "start": "2026-01-01",
          "end": "2026-01-03"
        },
        {
          "uid": "1673574b-5fd1-427a-97ed-c0c63bc9d26f",
          "summary": "Reservation",
          "type": "reservation",
          "start": "2026-01-16",
          "end": "2026-01-19"
        },
        {
          "uid": "dcfa57b2-a2a3-481e-8fe2-eb06a039d349",
          "summary": "Owner Block",
          "type": "closed",
          "start": "2026-01-21",
          "end": "2026-01-24"
        },
        {
          "uid": "59c6aed8-d2fa-4b9b-ae6e-41c3c9e54796",
          "summary": "Reservation",
          "type": "reservation",
          "start": "2026-01-24",
          "end": "2026-01-27"
        },
        {
          "uid": "b8923d50-19b9-48d8-a99a-bbcc2b124f01",
          "summary": "Owner Block",
          "type": "closed",
          "start": "2026-01-27",
          "end": "2026-01-30"
        },
        {
          "uid": "e95107bd-a4f1-4464-b769-69a31add7032",
          "summary": "Reservation",
          "type": "reservation",
          "start": "2026-01-30",
          "end": "2026-02-01"
        },
        {
          "uid": "1a2c706b-48b7-484c-ab9f-36e326e6a66f",
          "summary": "Owner Block",
          "type": "closed",
          "start": "2026-02-01",
          "end": "2026-02-05"
        },
        {
          "uid": "5d5bcec3-f427-4ab0-aff4-af6a9769f4d8",
          "summary": "Reservation",
          "type": "reservation",
          "start": "2026-02-05",
          "end": "2026-02-08"
        },
        {
          "uid": "5934c6a8-6bbb-4637-af15-8a18a65d31ca",
          "summary": "Reservation",
          "type": "reservation",
          "start": "2026-02-13",
          "end": "2026-02-16"
        },
        {
          "uid": "f7012410-4016-46bf-b2f9-097222bdb7fd",
          "summary": "Reservation",
          "type": "reservation",
          "start": "2026-02-20",
          "end": "2026-02-22"
        },
        {
          "uid": "96cf31ee-aef1-4c51-80c5-2db54330387a",
          "summary": "Owner Block",
          "type": "closed",
          "start": "2026-02-22",
          "end": "2026-02-23"
        },
        {
          "uid": "bfc6983e-08ee-4155-a5fe-033efe3cc4f1",
          "summary": "Reservation",
          "type": "reservation",
          "start": "2026-02-27",
          "end": "2026-03-01"
        },
        {
          "uid": "ab0f4d40-475a-447d-a19f-daeed7d9f8b6",
          "summary": "Reservation",
          "type": "reservation",
          "start": "2026-04-03",
          "end": "2026-04-05"
        },
        {
          "uid": "0d7ba285-6e2d-4957-b9b4-b4e809cd7cdf",
          "summary": "Owner Block",
          "type": "closed",
          "start": "2026-04-18",
          "end": "2026-04-22"
        },
        {
          "uid": "32d573bb-0bf7-49eb-af51-128598983828",
          "summary": "Reservation",
          "type": "reservation",
          "start": "2026-05-13",
          "end": "2026-05-17"
        }
      ]
    },
    {
      "name": "67 Squirrel Tree Ln",
      "events": [
        {
          "uid": "7ea72f7a-3538-4a1e-afa3-454b33192bc6",
          "summary": "Reservation",
          "type": "reservation",
          "start": "2026-01-01",
          "end": "2026-01-04"
        },
        {
          "uid": "9c8eeae1-0cd8-4038-8832-5acbadce1f87",
          "summary": "Reservation",
          "type": "reservation",
          "start": "2026-01-09",
          "end": "2026-01-12"
        },
        {
          "uid": "fc097d10-498a-4ec0-802b-c74e37012074",
          "summary": "Owner Block",
          "type": "closed",
          "start": "2026-01-12",
          "end": "2026-01-16"
        },
        {
          "uid": "6866f2f6-00aa-4c7a-8df8-8a08486d6cbd",
          "summary": "Reservation",
          "type": "reservation",
          "start": "2026-01-16",
          "end": "2026-01-19"
        },
        {
          "uid": "fe512310-2c77-4dd1-bd8c-64d415d54e8f",
          "summary": "Owner Block",
          "type": "closed",
          "start": "2026-01-21",
          "end": "2026-01-23"
        },
        {
          "uid": "ece6963c-ad3a-4cfc-9715-430d3e68c8c7",
          "summary": "Reservation",
          "type": "reservation",
          "start": "2026-01-23",
          "end": "2026-01-26"
        },
        {
          "uid": "c8c51655-83f3-494b-b017-b3ffd2cf4e1e",
          "summary": "Owner Block",
          "type": "closed",
          "start": "2026-01-26",
          "end": "2026-01-29"
        },
        {
          "uid": "19fc4dbc-e0fb-4d14-9697-725504c4df55",
          "summary": "Reservation",
          "type": "reservation",
          "start": "2026-01-29",
          "end": "2026-01-31"
        },
        {
          "uid": "62e7be44-bab1-40b7-9ef2-2382e9cbc9a7",
          "summary": "Reservation",
          "type": "reservation",
          "start": "2026-01-31",
          "end": "2026-02-02"
        },
        {
          "uid": "33431a30-a3d9-4c5f-a53d-bf911b282e76",
          "summary": "Reservation",
          "type": "reservation",
          "start": "2026-02-06",
          "end": "2026-02-09"
        },
        {
          "uid": "61d8485c-b5f3-45b3-b25c-a560be345ad1",
          "summary": "Reservation",
          "type": "reservation",
          "start": "2026-02-13",
          "end": "2026-02-16"
        },
        {
          "uid": "065af72f-974f-4379-867d-e3ac71960c45",
          "summary": "Reservation",
          "type": "reservation",
          "start": "2026-02-20",
          "end": "2026-02-22"
        },
        {
          "uid": "203c050d-ce25-446a-9c98-3a960206322f",
          "summary": "Owner Block",
          "type": "closed",
          "start": "2026-02-22",
          "end": "2026-02-23"
        },
        {
          "uid": "69b123ec-9bfd-4e8d-9974-a4439cf4c4b7",
          "summary": "Reservation",
          "type": "reservation",
          "start": "2026-02-27",
          "end": "2026-03-01"
        },
        {
          "uid": "57abbb10-c975-4bac-8cbc-37b5af303a2f",
          "summary": "Reservation",
          "type": "reservation",
          "start": "2026-03-06",
          "end": "2026-03-08"
        },
        {
          "uid": "819a26f1-1d39-4f10-892c-63dfd1f7d27b",
          "summary": "Reservation",
          "type": "reservation",
          "start": "2026-03-13",
          "end": "2026-03-15"
        },
        {
          "uid": "74e0dadc-5fe6-4ff4-8c9d-8ea8661190dc",
          "summary": "Reservation",
          "type": "reservation",
          "start": "2026-03-20",
          "end": "2026-03-22"
        },
        {
          "uid": "3213fe98-34ab-4e74-a05a-9272fc78307d",
          "summary": "Reservation",
          "type": "reservation",
          "start": "2026-03-27",
          "end": "2026-03-29"
        },
        {
          "uid": "d3e9eef8-c9f3-4f2d-a89e-50d9a786d984",
          "summary": "Reservation",
          "type": "reservation",
          "start": "2026-04-03",
          "end": "2026-04-06"
        },
        {
          "uid": "acf6469a-6cbc-48ff-9608-a67d512b9b14",
          "summary": "Reservation",
          "type": "reservation",
          "start": "2026-04-09",
          "end": "2026-04-12"
        }
      ]
    }
  ]
}